[
  {
    "_id": "dev",
    "name": "Development",
    "color": "bg-blue-100 text-blue-800 dark:bg-blue-900 dark:text-blue-300",
    "memberIds": [],
    "createdAt": "2026-04-07T02:53:21.134Z",
    "updatedAt": "2026-04-07T02:53:21.134Z"
  },
  {
    "_id": "qa",
    "name": "Quality Assurance",
    "color": "bg-green-100 text-green-800 dark:bg-green-900 dark:text-green-300",
    "memberIds": [],
    "createdAt": "2026-04-07T02:53:21.134Z",
    "updatedAt": "2026-04-07T02:53:21.134Z"
  },
  {
    "_id": "design",
    "name": "Design",
    "color": "bg-purple-100 text-purple-800 dark:bg-purple-900 dark:text-purple-300",
    "memberIds": [],
    "createdAt": "2026-04-07T02:53:21.134Z",
    "updatedAt": "2026-04-07T02:53:21.134Z"
  },
  {
    "_id": "product",
    "name": "Product",
    "color": "bg-orange-100 text-orange-800 dark:bg-orange-900 dark:text-orange-300",
    "memberIds": [],
    "createdAt": "2026-04-07T02:53:21.134Z",
    "updatedAt": "2026-04-07T02:53:21.134Z"
  },
  {
    "_id": "marketing",
    "name": "Marketing",
    "color": "bg-pink-100 text-pink-800 dark:bg-pink-900 dark:text-pink-300",
    "memberIds": [
      "people_0",
      "people_1",
      "people_2",
      "people_3"
    ],
    "createdAt": "2026-04-07T02:53:21.134Z",
    "updatedAt": "2026-04-07T02:53:21.134Z"
  },
  {
    "_id": "store",
    "name": "Cửa hàng",
    "color": "bg-teal-100 text-teal-800 dark:bg-teal-900 dark:text-teal-300",
    "memberIds": [],
    "createdAt": "2026-04-17T00:00:00.000Z",
    "updatedAt": "2026-04-17T00:00:00.000Z"
  }
]
